ptinaska/__init__.py
ptinaska/__main__.py
ptinaska/cli.py
ptinaska/version.py
ptinaska-0.1.2.dist-info/LICENSE.txt
ptinaska-0.1.2.dist-info/METADATA
ptinaska-0.1.2.dist-info/WHEEL
ptinaska-0.1.2.dist-info/top_level.txt
ptinaska-0.1.2.dist-info/RECORD
